LICENSE
MANIFEST.in
README.rst
setup.py
bin/possum
possum/__init__.py
possum.egg-info/PKG-INFO
possum.egg-info/SOURCES.txt
possum.egg-info/dependency_links.txt
possum.egg-info/not-zip-safe
possum.egg-info/requires.txt
possum.egg-info/top_level.txt