Metadata-Version: 1.2
Name: possum
Version: 1.4.4
Summary: A packaging tool for Python AWS serverless applications.
Home-page: https://github.com/brysontyrrell/Possum
Author: Bryson Tyrrell
Author-email: bryson.tyrrell@gmail.com
License: MIT
Platform: UNKNOWN
Classifier: Development Status :: 5 - Production/Stable
Classifier: License :: OSI Approved :: MIT License
Classifier: Programming Language :: Python
Classifier: Programming Language :: Python :: 3.6
Classifier: Topic :: Software Development :: Build Tools
Requires-Python: >=3.6
